gnutools/__init__.py
gnutools/functional.py
gnutools/audio/__init__.py
gnutools/audio/functional.py
gnutools/concurrent/__init__.py
gnutools/fs/__init__.py
gnutools/fs/functional.py
gnutools/grid/__init__.py
gnutools/grid/grid.py
gnutools/remote/__init__.py
gnutools/remote/functional.py
gnutools/tests/__init__.py
gnutools/tests/__main__.py
gnutools/tests/functional.py
gnutools/utils/__init__.py
gnutools/utils/functional.py
gnutools_python-2.3.5.dist-info/LICENSE
gnutools_python-2.3.5.dist-info/METADATA
gnutools_python-2.3.5.dist-info/WHEEL
gnutools_python-2.3.5.dist-info/top_level.txt
gnutools_python-2.3.5.dist-info/RECORD
