Metadata-Version: 2.1
Name: gnutools-python
Version: 2.3.5
Summary: GNU Tools for python
Home-page: https://github.com/JeanMaximilienCadic/gnutools-python
Author: Jean Maximilien Cadic
Author-email: git@cadic.jp
License: MIT
Classifier: Programming Language :: Python :: 3.6
Classifier: License :: OSI Approved :: MIT License
Requires-Python: >=3.6
License-File: LICENSE
Requires-Dist: pyYaml
Requires-Dist: numpy
Requires-Dist: rich
Requires-Dist: tabulate
Requires-Dist: pandas
Requires-Dist: tqdm
Requires-Dist: gdown
Requires-Dist: h5py
